devtools_timestamp/__init__.py
devtools_timestamp-1.0.1.dist-info/METADATA
devtools_timestamp-1.0.1.dist-info/WHEEL
devtools_timestamp-1.0.1.dist-info/top_level.txt
devtools_timestamp-1.0.1.dist-info/RECORD
