Metadata-Version: 2.1
Name: devtools_timestamp
Version: 1.0.1
Summary: Timestamp converter
Home-page: https://devtools.at/tools/timestamp
Author: DevTools.at
Author-email: hello@devtools.at
Project-URL: Homepage, https://devtools.at/tools/timestamp
Project-URL: Repository, https://github.com/devtools-at/timestamp
Classifier: Development Status :: 4 - Beta
Classifier: Intended Audience :: Developers
Classifier: License :: OSI Approved :: MIT License
Classifier: Programming Language :: Python :: 3
Requires-Python: >=3.8
